aiblackbox/__init__.py
aiblackbox/blackbox.py
aiblackbox/config.py
aiblackbox/generic_patch.py
aiblackbox/utils.py
aiblackbox/storage/__init__.py
aiblackbox/storage/local.py
aiblackbox/storage/s3.py
aiblackbox-0.1.2.dist-info/licenses/LICENSE
aiblackbox-0.1.2.dist-info/METADATA
aiblackbox-0.1.2.dist-info/WHEEL
aiblackbox-0.1.2.dist-info/top_level.txt
aiblackbox-0.1.2.dist-info/RECORD
