Metadata-Version: 2.4
Name: aiblackbox
Version: 0.1.2
Summary: Plug-and-play AI/ML function call logging with replay and patching
Author-email: Hayes Gladden <your@email.com>
License: MIT
Project-URL: Homepage, https://github.com/yourusername/AiBlackBox
Project-URL: Issues, https://github.com/yourusername/AiBlackBox/issues
Requires-Python: >=3.8
License-File: LICENSE
Dynamic: license-file
